doenova/__init__.py
doenova-0.2.2.dist-info/METADATA
doenova-0.2.2.dist-info/WHEEL
doenova-0.2.2.dist-info/top_level.txt
doenova-0.2.2.dist-info/RECORD
