Metadata-Version: 2.1
Name: doenova
Version: 0.2.2
Summary: Simple DOE and ANOVA package for Python 3
Home-page: http://doenova.tripli.ca/
Author: Francis B. Lavoie
Author-email: francis.b.lavoie@usherbrooke.ca
License: UNKNOWN
Platform: UNKNOWN
Classifier: Programming Language :: Python :: 3
Classifier: License :: OSI Approved :: BSD License
Classifier: Operating System :: OS Independent
